{
"meta":{"test_sets":[],"test_metrics":[],"learn_metrics":[{"best_value":"Min","name":"RMSE"}],"launch_mode":"Train","parameters":"","iteration_count":100,"learn_sets":["learn"],"name":"experiment"},
"iterations":[
{"learn":[2902903.748],"iteration":0,"passed_time":0.005842396767,"remaining_time":0.5783972799},
{"learn":[2849371.228],"iteration":1,"passed_time":0.01092425098,"remaining_time":0.535288298},
{"learn":[2794844.1],"iteration":2,"passed_time":0.01575733936,"remaining_time":0.5094873061},
{"learn":[2753799.257],"iteration":3,"passed_time":0.02015493616,"remaining_time":0.4837184679},
{"learn":[2705281.644],"iteration":4,"passed_time":0.0248583845,"remaining_time":0.4723093055},
{"learn":[2671249.466],"iteration":5,"passed_time":0.02964496375,"remaining_time":0.4644377654},
{"learn":[2646414.492],"iteration":6,"passed_time":0.03570431918,"remaining_time":0.4743573834},
{"learn":[2619987.187],"iteration":7,"passed_time":0.04053547375,"remaining_time":0.4661579482},
{"learn":[2593267.11],"iteration":8,"passed_time":0.04496052555,"remaining_time":0.4546008694},
{"learn":[2578943.633],"iteration":9,"passed_time":0.04996209351,"remaining_time":0.4496588416},
{"learn":[2556877.512],"iteration":10,"passed_time":0.05502567832,"remaining_time":0.445207761},
{"learn":[2543542.055],"iteration":11,"passed_time":0.05883512328,"remaining_time":0.4314575707},
{"learn":[2532039.356],"iteration":12,"passed_time":0.06302643682,"remaining_time":0.421792308},
{"learn":[2515653.433],"iteration":13,"passed_time":0.06798128546,"remaining_time":0.417599325},
{"learn":[2503873.689],"iteration":14,"passed_time":0.07214357491,"remaining_time":0.4088135912},
{"learn":[2497365.337],"iteration":15,"passed_time":0.07589136183,"remaining_time":0.3984296496},
{"learn":[2491547.701],"iteration":16,"passed_time":0.08001006757,"remaining_time":0.3906373887},
{"learn":[2484935.844],"iteration":17,"passed_time":0.08437233917,"remaining_time":0.3843628784},
{"learn":[2479524.948],"iteration":18,"passed_time":0.08817882663,"remaining_time":0.3759202609},
{"learn":[2473165.239],"iteration":19,"passed_time":0.09196242957,"remaining_time":0.3678497183},
{"learn":[2469396.617],"iteration":20,"passed_time":0.09562997265,"remaining_time":0.3597508495},
{"learn":[2461668.064],"iteration":21,"passed_time":0.1005047124,"remaining_time":0.3563348895},
{"learn":[2458446.486],"iteration":22,"passed_time":0.1059212498,"remaining_time":0.3546059231},
{"learn":[2455734.93],"iteration":23,"passed_time":0.1101039331,"remaining_time":0.3486624547},
{"learn":[2450274.503],"iteration":24,"passed_time":0.1147055128,"remaining_time":0.3441165383},
{"learn":[2441699.578],"iteration":25,"passed_time":0.1192866245,"remaining_time":0.339508085},
{"learn":[2436592.787],"iteration":26,"passed_time":0.123599057,"remaining_time":0.3341752282},
{"learn":[2434335.623],"iteration":27,"passed_time":0.1274451521,"remaining_time":0.3277161055},
{"learn":[2431753.793],"iteration":28,"passed_time":0.132476405,"remaining_time":0.3243387847},
{"learn":[2426185.832],"iteration":29,"passed_time":0.1363637923,"remaining_time":0.3181821821},
{"learn":[2421767.806],"iteration":30,"passed_time":0.140129373,"remaining_time":0.3119008624},
{"learn":[2417830.171],"iteration":31,"passed_time":0.1436346597,"remaining_time":0.305223652},
{"learn":[2416862.3],"iteration":32,"passed_time":0.1477789324,"remaining_time":0.3000360143},
{"learn":[2413851.946],"iteration":33,"passed_time":0.1518634019,"remaining_time":0.2947936625},
{"learn":[2411113.925],"iteration":34,"passed_time":0.1555417436,"remaining_time":0.288863238},
{"learn":[2407935.959],"iteration":35,"passed_time":0.1620982785,"remaining_time":0.2881747173},
{"learn":[2399965.688],"iteration":36,"passed_time":0.1659111187,"remaining_time":0.2824973102},
{"learn":[2397265.011],"iteration":37,"passed_time":0.169399266,"remaining_time":0.276388276},
{"learn":[2391832.525],"iteration":38,"passed_time":0.1732827503,"remaining_time":0.271031994},
{"learn":[2390432.716],"iteration":39,"passed_time":0.1773982459,"remaining_time":0.2660973688},
{"learn":[2386079.721],"iteration":40,"passed_time":0.181343563,"remaining_time":0.2609578102},
{"learn":[2384009.949],"iteration":41,"passed_time":0.1850162552,"remaining_time":0.2554986381},
{"learn":[2383211.918],"iteration":42,"passed_time":0.1890776901,"remaining_time":0.2506378683},
{"learn":[2381666.079],"iteration":43,"passed_time":0.1949098628,"remaining_time":0.2480670982},
{"learn":[2377545.556],"iteration":44,"passed_time":0.1992010869,"remaining_time":0.2434679951},
{"learn":[2372748.245],"iteration":45,"passed_time":0.2028272732,"remaining_time":0.2381015816},
{"learn":[2370153.502],"iteration":46,"passed_time":0.2065666718,"remaining_time":0.2329368853},
{"learn":[2369230.37],"iteration":47,"passed_time":0.2108905582,"remaining_time":0.2284647714},
{"learn":[2367732.678],"iteration":48,"passed_time":0.2150022253,"remaining_time":0.2237778264},
{"learn":[2366132.109],"iteration":49,"passed_time":0.2187036713,"remaining_time":0.2187036713},
{"learn":[2362691.34],"iteration":50,"passed_time":0.2224176962,"remaining_time":0.2136954336},
{"learn":[2361138.142],"iteration":51,"passed_time":0.2267225546,"remaining_time":0.2092823581},
{"learn":[2360128.122],"iteration":52,"passed_time":0.2304146756,"remaining_time":0.2043299953},
{"learn":[2352153.274],"iteration":53,"passed_time":0.2343830166,"remaining_time":0.1996596068},
{"learn":[2348895.025],"iteration":54,"passed_time":0.2384819019,"remaining_time":0.1951215561},
{"learn":[2344540.976],"iteration":55,"passed_time":0.2424265697,"remaining_time":0.190478019},
{"learn":[2343078.134],"iteration":56,"passed_time":0.2462657246,"remaining_time":0.1857794063},
{"learn":[2339385.105],"iteration":57,"passed_time":0.2501223879,"remaining_time":0.1811231085},
{"learn":[2338305.42],"iteration":58,"passed_time":0.2537032949,"remaining_time":0.1763022897},
{"learn":[2336152.076],"iteration":59,"passed_time":0.257826896,"remaining_time":0.1718845973},
{"learn":[2333387.541],"iteration":60,"passed_time":0.2624484319,"remaining_time":0.1677948991},
{"learn":[2332574.476],"iteration":61,"passed_time":0.2662129276,"remaining_time":0.1631627621},
{"learn":[2329568.185],"iteration":62,"passed_time":0.2697564314,"remaining_time":0.1584283804},
{"learn":[2328823.222],"iteration":63,"passed_time":0.274520399,"remaining_time":0.1544177245},
{"learn":[2327588.792],"iteration":64,"passed_time":0.2786422515,"remaining_time":0.1500381354},
{"learn":[2325467.806],"iteration":65,"passed_time":0.2826363014,"remaining_time":0.1456005189},
{"learn":[2322947.656],"iteration":66,"passed_time":0.2861323111,"remaining_time":0.1409308398},
{"learn":[2321555.199],"iteration":67,"passed_time":0.2897667649,"remaining_time":0.1363608305},
{"learn":[2320331.8],"iteration":68,"passed_time":0.2937298049,"remaining_time":0.1319655645},
{"learn":[2316829.546],"iteration":69,"passed_time":0.2972943561,"remaining_time":0.1274118669},
{"learn":[2315689.492],"iteration":70,"passed_time":0.3010089832,"remaining_time":0.1229473312},
{"learn":[2311562.052],"iteration":71,"passed_time":0.3046198786,"remaining_time":0.1184632861},
{"learn":[2310510.124],"iteration":72,"passed_time":0.3090792353,"remaining_time":0.1143169774},
{"learn":[2307167.139],"iteration":73,"passed_time":0.3131584185,"remaining_time":0.1100286335},
{"learn":[2303504.658],"iteration":74,"passed_time":0.3169640401,"remaining_time":0.10565468},
{"learn":[2296380.785],"iteration":75,"passed_time":0.3206373315,"remaining_time":0.1012538942},
{"learn":[2294345.514],"iteration":76,"passed_time":0.3245860785,"remaining_time":0.0969542832},
{"learn":[2293799.799],"iteration":77,"passed_time":0.3283839572,"remaining_time":0.09262111612},
{"learn":[2286396.168],"iteration":78,"passed_time":0.3320978305,"remaining_time":0.08827917014},
{"learn":[2285712.621],"iteration":79,"passed_time":0.3363595555,"remaining_time":0.08408988887},
{"learn":[2285065.572],"iteration":80,"passed_time":0.3403910934,"remaining_time":0.07984482439},
{"learn":[2281954.664],"iteration":81,"passed_time":0.3441374982,"remaining_time":0.07554237766},
{"learn":[2279699.537],"iteration":82,"passed_time":0.3476893535,"remaining_time":0.07121348205},
{"learn":[2273002.443],"iteration":83,"passed_time":0.3512247073,"remaining_time":0.06689994424},
{"learn":[2269885.14],"iteration":84,"passed_time":0.3551927865,"remaining_time":0.06268107997},
{"learn":[2268919.512],"iteration":85,"passed_time":0.3587575988,"remaining_time":0.0584023998},
{"learn":[2264531.625],"iteration":86,"passed_time":0.3624123198,"remaining_time":0.05415356503},
{"learn":[2260616.931],"iteration":87,"passed_time":0.3658914099,"remaining_time":0.04989428316},
{"learn":[2260018.925],"iteration":88,"passed_time":0.3695675301,"remaining_time":0.04567688574},
{"learn":[2258457.851],"iteration":89,"passed_time":0.3731718298,"remaining_time":0.04146353664},
{"learn":[2257351.679],"iteration":90,"passed_time":0.3767077585,"remaining_time":0.03725681128},
{"learn":[2255649.48],"iteration":91,"passed_time":0.3802330685,"remaining_time":0.03306374509},
{"learn":[2253884.966],"iteration":92,"passed_time":0.3838029952,"remaining_time":0.02888839749},
{"learn":[2250055.719],"iteration":93,"passed_time":0.3879099041,"remaining_time":0.02476020664},
{"learn":[2248956.177],"iteration":94,"passed_time":0.3920073143,"remaining_time":0.02063196391},
{"learn":[2245381.531],"iteration":95,"passed_time":0.3955563954,"remaining_time":0.01648151648},
{"learn":[2243985.66],"iteration":96,"passed_time":0.399124035,"remaining_time":0.01234404232},
{"learn":[2241884.87],"iteration":97,"passed_time":0.4035682906,"remaining_time":0.008236087564},
{"learn":[2239937.322],"iteration":98,"passed_time":0.4075732826,"remaining_time":0.004116901844},
{"learn":[2238615.224],"iteration":99,"passed_time":0.4110583385,"remaining_time":0}
]}